plinko/__init__.py
plinko/plinko_hadoop.py
plinko/plinko_postgres.py
plinko/plinko_redshift.py
plinko/plinko_s3.py
plinko/plinko_s3R.py
plinko/plinko_sql.py
plinko/configurations/__init__.py
plinko/configurations/configure_api_key.py
plinko/configurations/configure_environment.py
plinko/configurations/configure_username.py
plinko/utils/__init__.py
plinko/zoltar/__init__.py
plinko/zoltar/zoltar_ask.py
plinko/zoltar/zoltar_list.py
plinko-0.2.1.dist-info/LICENSE.txt
plinko-0.2.1.dist-info/METADATA
plinko-0.2.1.dist-info/WHEEL
plinko-0.2.1.dist-info/top_level.txt
plinko-0.2.1.dist-info/RECORD
