Metadata-Version: 2.1
Name: plinko
Version: 0.2.1
Summary: Python equivalent to the internal R library, klink, for establishing remote connections to data sources
Home-page: https://pypi.org/project/plinko
Author: Nat Hawkins, Mike Chappelow
Author-email: nat.hawkins@kellogg.com, michael.chappelow@kellogg.com
License: LICENSE.txt
Platform: UNKNOWN
License-File: LICENSE.txt
